ejdate/__init__.py
ejdate/core.py
ejdate/exceptions.py
ejdate/formats.py
ejdate/utils.py
ejdate-0.1.0.dist-info/licenses/LICENSE
ejdate-0.1.0.dist-info/METADATA
ejdate-0.1.0.dist-info/WHEEL
ejdate-0.1.0.dist-info/top_level.txt
ejdate-0.1.0.dist-info/RECORD
